audio_engine/__init__.py
audio_engine/base.py
audio_engine/sigproc.py
audio_engine-0.1.dist-info/LICENSE
audio_engine-0.1.dist-info/METADATA
audio_engine-0.1.dist-info/WHEEL
audio_engine-0.1.dist-info/top_level.txt
audio_engine-0.1.dist-info/RECORD
