Metadata-Version: 2.1
Name: audio-engine
Version: 0.1
Summary: This library provides common speech features for ASR including MFCCs and filterbank energies.
Home-page: https://github.com/Jss-on/audio_engine
Author: Jession Diwangan
Author-email: jessiondiwangan@gmail.com
License: MIT
License-File: LICENSE
Requires-Dist: scipy (>=1.11.1)
Requires-Dist: numpy (>=1.23.5)
